src/__init__.py
src/matmul.py
tests/__init__.py
tests/test_matmul.py
matmul_package-0.1.dist-info/METADATA
matmul_package-0.1.dist-info/WHEEL
matmul_package-0.1.dist-info/top_level.txt
matmul_package-0.1.dist-info/RECORD
