Metadata-Version: 2.1
Name: matmul-package
Version: 0.1
Summary: A simple package for parallel matrix multiplication using joblib
Home-page: https://github.com/sazzad1779/matmul_package
Author: Md_sazzad_hossain
Author-email: sazzad1779@gmail.com
Classifier: Programming Language :: Python :: 3
Classifier: Operating System :: OS Independent
Requires-Python: >=3.6
Requires-Dist: joblib
Requires-Dist: numpy
